setup.py
BitbucketSyncPlugin.egg-info/PKG-INFO
BitbucketSyncPlugin.egg-info/SOURCES.txt
BitbucketSyncPlugin.egg-info/dependency_links.txt
BitbucketSyncPlugin.egg-info/entry_points.txt
BitbucketSyncPlugin.egg-info/not-zip-safe
BitbucketSyncPlugin.egg-info/top_level.txt
bitbucketsync/__init__.py
bitbucketsync/api.py