Metadata-Version: 1.0
Name: BitbucketSyncPlugin
Version: 0.1.1
Summary: Sync Bitbucket repository with local repository used by Trac.
Home-page: http://mitar.tnode.com/
Author: Mitar
Author-email: mitar.trac@tnode.com
License: AGPLv3
Keywords: trac plugin
Platform: UNKNOWN
